gspl/__init__.py
gspl/_chunks.py
gspl/_decorators.py
gspl/_logger.py
gspl/_retrieval.py
gspl/_tokenizer.py
gspl/gspl.py
gspl_api-0.0.92.dist-info/LICENSE
gspl_api-0.0.92.dist-info/METADATA
gspl_api-0.0.92.dist-info/WHEEL
gspl_api-0.0.92.dist-info/top_level.txt
gspl_api-0.0.92.dist-info/RECORD
