Metadata-Version: 2.1
Name: gspl-api
Version: 0.0.92
Summary: GSPL: Gen-Selective Pseudo Labeling for Domain Adaptation, based on 🤗 Datasets and Serverless Inference API.
Keywords: language-models,retrieval,web-scraping,gpl,nlp,machine-learning,retrieval-augmented-generation,RAG,huggingface,generative-ai,llama,Mistral,inference-api,datasets,llm-as-judge
Classifier: Programming Language :: Python
Classifier: Programming Language :: Python :: 3
Classifier: Intended Audience :: Developers
Classifier: Intended Audience :: Science/Research
Classifier: Topic :: Scientific/Engineering :: Artificial Intelligence
Classifier: Topic :: Software Development
Classifier: Topic :: Software Development :: Libraries
Classifier: Topic :: Software Development :: Libraries :: Python Modules
License-File: LICENSE
